reversion/__init__.py
reversion/errors.py
reversion/middleware.py
reversion/models.py
reversion/revisions.py
reversion/signals.py
reversion/views.py
reversion/backends/__init__.py
reversion/backends/utils.py
reversion/backends/dynamodb/__init__.py
reversion/backends/dynamodb/app.py
reversion/backends/dynamodb/models.py
reversion/backends/dynamodb/queryset.py
reversion/backends/dynamodb/management/__init__.py
reversion/backends/dynamodb/management/commands/__init__.py
reversion/backends/dynamodb/management/commands/initdynamodbreversion.py
reversion/backends/sql/__init__.py
reversion/backends/sql/admin.py
reversion/backends/sql/app.py
reversion/backends/sql/models.py
reversion/backends/sql/management/__init__.py
reversion/backends/sql/management/commands/__init__.py
reversion/backends/sql/management/commands/createinitialrevisions.py
reversion/backends/sql/management/commands/deleterevisions.py
reversion/backends/sql/migrations/0001_squashed_0004_auto_20160611_1202.py
reversion/backends/sql/migrations/__init__.py
reversion/locale/ar/LC_MESSAGES/django.mo
reversion/locale/ar/LC_MESSAGES/django.po
reversion/locale/cs/LC_MESSAGES/django.mo
reversion/locale/cs/LC_MESSAGES/django.po
reversion/locale/da/LC_MESSAGES/django.mo
reversion/locale/da/LC_MESSAGES/django.po
reversion/locale/de/LC_MESSAGES/django.mo
reversion/locale/de/LC_MESSAGES/django.po
reversion/locale/es/LC_MESSAGES/django.mo
reversion/locale/es/LC_MESSAGES/django.po
reversion/locale/es_AR/LC_MESSAGES/django.mo
reversion/locale/es_AR/LC_MESSAGES/django.po
reversion/locale/fr/LC_MESSAGES/django.mo
reversion/locale/fr/LC_MESSAGES/django.po
reversion/locale/he/LC_MESSAGES/django.mo
reversion/locale/he/LC_MESSAGES/django.po
reversion/locale/it/LC_MESSAGES/django.mo
reversion/locale/it/LC_MESSAGES/django.po
reversion/locale/nb/LC_MESSAGES/django.mo
reversion/locale/nb/LC_MESSAGES/django.po
reversion/locale/nl/LC_MESSAGES/django.mo
reversion/locale/nl/LC_MESSAGES/django.po
reversion/locale/pl/LC_MESSAGES/django.mo
skip_django_reversion_pynamodb-0.2.0.dist-info/LICENSE
skip_django_reversion_pynamodb-0.2.0.dist-info/METADATA
skip_django_reversion_pynamodb-0.2.0.dist-info/WHEEL
skip_django_reversion_pynamodb-0.2.0.dist-info/top_level.txt
skip_django_reversion_pynamodb-0.2.0.dist-info/RECORD
