Metadata-Version: 2.1
Name: skip-django-reversion-pynamodb
Version: 0.2.0
Summary: An extension to the Django web framework that provides version control for model instances.
Home-page: http://github.com/skip-pay/django-reversion-pynamodb
Author: Dave Hall,Lubos Matl
Author-email: dave@etianen.com, matllubos@gmail.com
License: BSD
Classifier: Development Status :: 5 - Production/Stable
Classifier: Environment :: Web Environment
Classifier: Intended Audience :: Developers
Classifier: License :: OSI Approved :: BSD License
Classifier: Operating System :: OS Independent
Classifier: Programming Language :: Python
Classifier: Programming Language :: Python :: 3.6
Classifier: Programming Language :: Python :: 3.7
Classifier: Programming Language :: Python :: 3.8
Classifier: Framework :: Django
Requires-Python: >=3.8
License-File: LICENSE
Requires-Dist: django >=4.2
Requires-Dist: import-string >=0.1.0
Provides-Extra: dynamodb
Requires-Dist: skip-pydjamodb >=0.1.0 ; extra == 'dynamodb'
Requires-Dist: pynamodb ==5.3.4 ; extra == 'dynamodb'
